openstack_doc_tools-4.0.1.data/data/share/openstack-doc-tools/sitemap/README.rst
openstack_doc_tools-4.0.1.data/data/share/openstack-doc-tools/sitemap/__init__.py
openstack_doc_tools-4.0.1.data/data/share/openstack-doc-tools/sitemap/scrapy.cfg
openstack_doc_tools-4.0.1.data/data/share/openstack-doc-tools/sitemap/transform-sitemap.xslt
openstack_doc_tools-4.0.1.data/data/share/openstack-doc-tools/sitemap/generator/__init__.py
openstack_doc_tools-4.0.1.data/data/share/openstack-doc-tools/sitemap/generator/pipelines.py
openstack_doc_tools-4.0.1.data/data/share/openstack-doc-tools/sitemap/generator/settings.py
openstack_doc_tools-4.0.1.data/data/share/openstack-doc-tools/sitemap/generator/spiders/__init__.py
openstack_doc_tools-4.0.1.data/data/share/openstack-doc-tools/sitemap/generator/spiders/sitemap_file.py
openstack_doc_tools-4.0.1.data/scripts/doc-tools-build-rst
openstack_doc_tools-4.0.1.data/scripts/doc-tools-check-languages
os_doc_tools/__init__.py
os_doc_tools/version.py
openstack_doc_tools-4.0.1.dist-info/AUTHORS
openstack_doc_tools-4.0.1.dist-info/LICENSE
openstack_doc_tools-4.0.1.dist-info/METADATA
openstack_doc_tools-4.0.1.dist-info/WHEEL
openstack_doc_tools-4.0.1.dist-info/pbr.json
openstack_doc_tools-4.0.1.dist-info/top_level.txt
openstack_doc_tools-4.0.1.dist-info/RECORD
