Metadata-Version: 2.1
Name: openstack-doc-tools
Version: 4.0.1
Summary: Tools for OpenStack Documentation
Home-page: https://docs.openstack.org/openstack-doc-tools/latest/
Author: OpenStack Documentation
Author-email: openstack-discuss@lists.openstack.org
Classifier: Environment :: OpenStack
Classifier: Intended Audience :: Information Technology
Classifier: Intended Audience :: System Administrators
Classifier: License :: OSI Approved :: Apache Software License
Classifier: Operating System :: POSIX :: Linux
Classifier: Programming Language :: Python
Classifier: Programming Language :: Python :: Implementation :: CPython
Classifier: Programming Language :: Python :: 3 :: Only
Classifier: Programming Language :: Python :: 3
Classifier: Programming Language :: Python :: 3.8
Classifier: Programming Language :: Python :: 3.9
Classifier: Programming Language :: Python :: 3.10
Classifier: Programming Language :: Python :: 3.11
Requires-Python: >=3.8
License-File: LICENSE
License-File: AUTHORS
Requires-Dist: pbr !=2.1.0,>=2.0.0
Requires-Dist: iso8601 >=0.1.11
Requires-Dist: lxml >=4.5.0
Requires-Dist: docutils >=0.11
Requires-Dist: sphinx !=2.1.0,>=2.0.0
Requires-Dist: PyYAML >=3.13
